pytraits/__init__.py
pytraits/combiner.py
pytraits/extendable.py
pytraits/setproperty.py
pytraits/trait_composer.py
pytraits/core/__init__.py
pytraits/core/base/__init__.py
pytraits/core/base/inspectors.py
pytraits/core/composing/__init__.py
pytraits/core/composing/compiler.py
pytraits/core/composing/composer.py
pytraits/core/composing/resolutions.py
pytraits/core/composing/traits.py
pytraits/core/primitives/__init__.py
pytraits/core/primitives/class_object.py
pytraits/core/primitives/instance_object.py
pytraits/core/primitives/property_object.py
pytraits/core/primitives/routine_object.py
pytraits/core/primitives/trait_object.py
pytraits/core/primitives/unidentified_object.py
pytraits/support/__init__.py
pytraits/support/errors.py
pytraits/support/factory.py
pytraits/support/inspector.py
pytraits/support/magic.py
pytraits/support/singleton.py
pytraits/support/utils.py
py3traits-1.2.1.dist-info/AUTHORS.rst
py3traits-1.2.1.dist-info/LICENSE
py3traits-1.2.1.dist-info/METADATA
py3traits-1.2.1.dist-info/WHEEL
py3traits-1.2.1.dist-info/top_level.txt
py3traits-1.2.1.dist-info/RECORD
