Metadata-Version: 2.1
Name: py3traits
Version: 1.2.1
Summary: Trait support for Python 3
Home-page: https://github.com/Debith/py3traits
Author: Teppo PerÃ¤
Author-email: debith-dev@outlook.com
License: Apache License 2
Keywords: traits
Classifier: Development Status :: 5 - Production/Stable
Classifier: Intended Audience :: Developers
Classifier: License :: OSI Approved :: BSD License
Classifier: Operating System :: Unix
Classifier: Operating System :: Microsoft :: Windows
Classifier: Programming Language :: Python
Classifier: Programming Language :: Python :: 3
Classifier: Programming Language :: Python :: 3.3
Classifier: Programming Language :: Python :: 3.4
Classifier: Topic :: Utilities
License-File: LICENSE
License-File: AUTHORS.rst
